odoo/addons/fetchmail_notify_error_to_sender_test/README.rst
odoo/addons/fetchmail_notify_error_to_sender_test/__init__.py
odoo/addons/fetchmail_notify_error_to_sender_test/__manifest__.py
odoo/addons/fetchmail_notify_error_to_sender_test/i18n/fetchmail_notify_error_to_sender_test.pot
odoo/addons/fetchmail_notify_error_to_sender_test/readme/CONTRIBUTORS.rst
odoo/addons/fetchmail_notify_error_to_sender_test/readme/DESCRIPTION.rst
odoo/addons/fetchmail_notify_error_to_sender_test/static/description/icon.png
odoo/addons/fetchmail_notify_error_to_sender_test/static/description/index.html
odoo/addons/fetchmail_notify_error_to_sender_test/tests/__init__.py
odoo/addons/fetchmail_notify_error_to_sender_test/tests/test_fetchmail_notify_error_to_sender.py
odoo13_addon_fetchmail_notify_error_to_sender_test-13.0.2.0.1.dist-info/METADATA
odoo13_addon_fetchmail_notify_error_to_sender_test-13.0.2.0.1.dist-info/WHEEL
odoo13_addon_fetchmail_notify_error_to_sender_test-13.0.2.0.1.dist-info/top_level.txt
odoo13_addon_fetchmail_notify_error_to_sender_test-13.0.2.0.1.dist-info/RECORD
